circ2/__init__.py
circ2/align.py
circ2/annotate.py
circ2/assemble.py
circ2/command_parse.py
circ2/denovo.py
circ2/dir_func.py
circ2/fast_circ.py
circ2/fetch_ucsc.py
circ2/genomic_interval.py
circ2/helper.py
circ2/parse.py
circ2/parser.py
circ2/rm_fusion_dup.py
circ2/version.py
test/__init__.py
test/test_annotate.py
test/test_denovo.py
test/test_parse.py
test/utils.py
CIRCexplorer2-2.3.8.dist-info/LICENSE.txt
CIRCexplorer2-2.3.8.dist-info/METADATA
CIRCexplorer2-2.3.8.dist-info/WHEEL
CIRCexplorer2-2.3.8.dist-info/entry_points.txt
CIRCexplorer2-2.3.8.dist-info/top_level.txt
CIRCexplorer2-2.3.8.dist-info/RECORD
