Metadata-Version: 2.1
Name: CIRCexplorer2
Version: 2.3.8
Summary: Circular RNA analysis toolkits
Home-page: https://github.com/YangLab/CIRCexplorer2
Author: Xiao-Ou Zhang
Author-email: zhangxiaoou@picb.ac.cn
License: MIT
Keywords: circular RNAs
Platform: UNKNOWN
Classifier: Development Status :: 5 - Production/Stable
Classifier: Intended Audience :: Science/Research
Classifier: Topic :: Scientific/Engineering :: Bio-Informatics
Classifier: License :: OSI Approved :: MIT License
Classifier: Programming Language :: Python :: 2
Classifier: Programming Language :: Python :: 3
Requires-Dist: requests
Requires-Dist: pysam (>=0.8.4)
Requires-Dist: pybedtools
Requires-Dist: scipy
Requires-Dist: docopt
